Serialkiller/Serializer.py
Serialkiller/__init__.py
Serialkiller/exc/DeserializationError.py
Serialkiller/exc/SerializationError.py
Serialkiller/exc/__init__.py
serialkiller_serializer-0.0.1.dist-info/LICENSE
serialkiller_serializer-0.0.1.dist-info/METADATA
serialkiller_serializer-0.0.1.dist-info/WHEEL
serialkiller_serializer-0.0.1.dist-info/top_level.txt
serialkiller_serializer-0.0.1.dist-info/RECORD
