Metadata-Version: 2.1
Name: serialkiller-serializer
Version: 0.0.1
Summary: A package for class serialization
Home-page: https://github.com/Mateus-SF/Serialkiller
Author: Mateus Ferreira
Author-email: mateus03ferreira04@gmail.com
License: MIT
Platform: UNKNOWN
License-File: LICENSE
